adp/__init__.py
adp/_adp_catalog.py
adp/_adp_share.py
adp/adp.py
adp/adp_ai.py
adp/adp_analytics.py
adp/adp_catalog.py
adp/adp_dataframe.py
adp/adp_ingest.py
adp/adp_insight.py
adp/adp_misc.py
adp/adp_share.py
adp/db_util.py
adp/requests.txt
adp/rest.py
datatransforms/LICENSE.txt
datatransforms/__init__.py
datatransforms/client.py
datatransforms/connection.py
datatransforms/connection_types.py
datatransforms/dataentity.py
datatransforms/dataflow.py
datatransforms/dataflow_load_options.py
datatransforms/dataload.py
datatransforms/models.py
datatransforms/project.py
datatransforms/schedule.py
datatransforms/secrets_util.py
datatransforms/variables.py
datatransforms/workbench.py
datatransforms/workflow.py
datatransforms/cli/__init__.py
datatransforms/cli/cli_common.py
datatransforms/cli/create_dev_env.py
datatransforms/cli/generate_data_entities.py
datatransforms/cli/utils.py
datatransforms/generators/__init__.py
datatransforms/generators/connection_type_generator.py
datatransforms/generators/dataflow_load_options.py
datatransforms/generators/df_load_options_generator.py
datatransforms/generators/metadata_code_generator.py
datatransforms/payloadutil/dataflow_payload.py
datatransforms/payloadutil/variable_payload.py
datatransforms/restclients/dataflow_api.py
datatransforms/restclients/runtime_api.py
oracle_data_studio-1.0.21.dist-info/licenses/LICENSE.txt
oracle_data_studio-1.0.21.dist-info/licenses/THIRD_PARTY_LICENSES.txt
oracle_data_studio-1.0.21.dist-info/METADATA
oracle_data_studio-1.0.21.dist-info/WHEEL
oracle_data_studio-1.0.21.dist-info/top_level.txt
oracle_data_studio-1.0.21.dist-info/RECORD
