Metadata-Version: 2.4
Name: oracle-data-studio
Version: 1.0.21
Summary: Python client for Oracle Data Studio Database Service
License: Copyright (c) 2023-2025, Oracle and/or its affiliates
Keywords: Oracle database,ORDS,Oracle database actions,Oracle Data Studio
Classifier: Programming Language :: Python :: 3
Classifier: Operating System :: OS Independent
Requires-Python: >=3.7
License-File: LICENSE.txt
License-File: THIRD_PARTY_LICENSES.txt
Requires-Dist: requests>=2.28.2
Requires-Dist: pandas>=2.2.3
Dynamic: license-file
